prediction_model_wrapper/__init__.py
prediction_model_wrapper/exceptions/__init__.py
prediction_model_wrapper/exceptions/invalid_module_path_error.py
prediction_model_wrapper/exceptions/invalid_type_error.py
prediction_model_wrapper/exceptions/model_not_loaded_error.py
prediction_model_wrapper/trained_model_data/__init__.py
prediction_model_wrapper/trained_model_data/trained_model_data.py
prediction_model_wrapper/trained_model_data/trained_model_data_keys.py
prediction_model_wrapper/wrapper/__init__.py
prediction_model_wrapper/wrapper/prediction_model_wrapper.py
tests/__init__.py
tests/dummy_objects.py
tests/test_prediction_model_wrapper.py
prediction_model_wrapper-1.0.14.0.dist-info/LICENSE
prediction_model_wrapper-1.0.14.0.dist-info/METADATA
prediction_model_wrapper-1.0.14.0.dist-info/WHEEL
prediction_model_wrapper-1.0.14.0.dist-info/top_level.txt
prediction_model_wrapper-1.0.14.0.dist-info/RECORD
