Metadata-Version: 2.1
Name: prediction-model-wrapper
Version: 1.0.14.0
Summary: A wrapper for the prediction model class acting as interface to the model class
Home-page: UNKNOWN
Author: lior.yehonatan
Author-email: lior.yehonatan@inel.com
License: BSD License
Platform: UNKNOWN
Requires-Python: >=3.6
Requires-Dist: swiss-common-utils
Requires-Dist: swiss-python
